{
    "metadata": {
        "source": "atmospheric_noise_raw.csv",
        "total_samples": 1000,
        "headers": [
            "X",
            "Y"
        ]
    },
    "structure": {
        "primitive_id": 200,
        "data_quanta": [
            {
                "X": 1,
                "Y": -0.7031873098624105
            },
            {
                "X": 2,
                "Y": -0.49028236278771464
            },
            {
                "X": 3,
                "Y": -0.3218143296501526
            },
            {
                "X": 4,
                "Y": -1.7550787171239868
            },
            {
                "X": 5,
                "Y": 0.20666447021383047
            },
            {
                "X": 6,
                "Y": 6.7260045808749265
            },
            {
                "X": 7,
                "Y": 8.627539671929927
            },
            {
                "X": 8,
                "Y": 0.3372170084417056
            },
            {
                "X": 9,
                "Y": 1.5488359716694058
            },
            {
                "X": 10,
                "Y": -1.3707365582609627
            },
            {
                "X": 11,
                "Y": 1.4252913986629026
            },
            {
                "X": 12,
                "Y": -0.2794639098029346
            },
            {
                "X": 13,
                "Y": -0.559627906760132
            },
            {
                "X": 14,
                "Y": 1.186383367445606
            },
            {
                "X": 15,
                "Y": 11.620625376580026
            },
            {
                "X": 16,
                "Y": -1.6912201576405048
            },
            {
                "X": 17,
                "Y": -0.6995228442321605
            },
            {
                "X": 18,
                "Y": 0.582962841937446
            },
            {
                "X": 19,
                "Y": 0.9782226298198076
            },
            {
                "X": 20,
                "Y": 6.617059666260057
            },
            {
                "X": 21,
                "Y": -1.3293954484318342
            },
            {
                "X": 22,
                "Y": -0.001454742266428668
            },
            {
                "X": 23,
                "Y": -1.3146526837845254
            },
            {
                "X": 24,
                "Y": -0.37961174341756554
            },
            {
                "X": 25,
                "Y": 1.265210647376645
            },
            {
                "X": 26,
                "Y": 0.12066774406890175
            },
            {
                "X": 27,
                "Y": 0.14794177849860185
            },
            {
                "X": 28,
                "Y": 2.8383056465109195
            },
            {
                "X": 29,
                "Y": -0.3568963241881448
            },
            {
                "X": 30,
                "Y": 0.00771783656034255
            },
            {
                "X": 31,
                "Y": 1.4782771611306014
            },
            {
                "X": 32,
                "Y": -0.957614628561729
            },
            {
                "X": 33,
                "Y": 1.3290081066145112
            },
            {
                "X": 34,
                "Y": -0.9858496301914452
            },
            {
                "X": 35,
                "Y": 0.47155720186813443
            },
            {
                "X": 36,
                "Y": 9.108415094267857
            },
            {
                "X": 37,
                "Y": 0.36701868900629514
            },
            {
                "X": 38,
                "Y": 1.1185547440864663
            },
            {
                "X": 39,
                "Y": -0.008389935119820476
            },
            {
                "X": 40,
                "Y": 0.46631537869506084
            },
            {
                "X": 41,
                "Y": 7.206806078110635
            },
            {
                "X": 42,
                "Y": -0.9016546538618192
            },
            {
                "X": 43,
                "Y": -1.0288426927914085
            },
            {
                "X": 44,
                "Y": 0.5696784209487935
            },
            {
                "X": 45,
                "Y": 0.6416647796503595
            },
            {
                "X": 46,
                "Y": 9.57545211578486
            },
            {
                "X": 47,
                "Y": 1.1931781372550891
            },
            {
                "X": 48,
                "Y": -1.0463003622367857
            },
            {
                "X": 49,
                "Y": 0.13988892063047142
            },
            {
                "X": 50,
                "Y": 5.118050660185757
            },
            {
                "X": 51,
                "Y": -0.13062311615876684
            },
            {
                "X": 52,
                "Y": -1.3102600178374146
            },
            {
                "X": 53,
                "Y": -2.171312418365992
            },
            {
                "X": 54,
                "Y": -1.0661814063812203
            },
            {
                "X": 55,
                "Y": 9.677598263327715
            },
            {
                "X": 56,
                "Y": 1.4663957475793472
            },
            {
                "X": 57,
                "Y": 0.8766430959089553
            },
            {
                "X": 58,
                "Y": 0.6699895801759875
            },
            {
                "X": 59,
                "Y": 5.706337468991293
            },
            {
                "X": 60,
                "Y": -0.25278543386503105
            },
            {
                "X": 61,
                "Y": 0.5679871068690735
            },
            {
                "X": 62,
                "Y": 0.30438785754883474
            },
            {
                "X": 63,
                "Y": 10.955045920157659
            },
            {
                "X": 64,
                "Y": -2.4564178268120704
            },
            {
                "X": 65,
                "Y": 0.25230702200569455
            },
            {
                "X": 66,
                "Y": 0.7631204238448489
            },
            {
                "X": 67,
                "Y": -1.5834546539063008
            },
            {
                "X": 68,
                "Y": 0.1980422815404921
            },
            {
                "X": 69,
                "Y": 0.08525222977484838
            },
            {
                "X": 70,
                "Y": 0.6405077502468317
            },
            {
                "X": 71,
                "Y": -0.7906581548664058
            },
            {
                "X": 72,
                "Y": 0.7711823952195227
            },
            {
                "X": 73,
                "Y": -1.9506777667257222
            },
            {
                "X": 74,
                "Y": -1.294010214921496
            },
            {
                "X": 75,
                "Y": -1.0735237659209356
            },
            {
                "X": 76,
                "Y": 0.030691091942390464
            },
            {
                "X": 77,
                "Y": 0.7741093450349587
            },
            {
                "X": 78,
                "Y": -0.8713963028878069
            },
            {
                "X": 79,
                "Y": 9.870260794723198
            },
            {
                "X": 80,
                "Y": 0.635789777188396
            },
            {
                "X": 81,
                "Y": 1.081671973516432
            },
            {
                "X": 82,
                "Y": -0.2827736615893422
            },
            {
                "X": 83,
                "Y": 1.5547879409170322
            },
            {
                "X": 84,
                "Y": -0.8583081351779684
            },
            {
                "X": 85,
                "Y": -0.2796504317480983
            },
            {
                "X": 86,
                "Y": -0.08542343253654935
            },
            {
                "X": 87,
                "Y": -0.21959764653062847
            },
            {
                "X": 88,
                "Y": -2.173598873816621
            },
            {
                "X": 89,
                "Y": 0.9063324273788009
            },
            {
                "X": 90,
                "Y": 9.020598229547893
            },
            {
                "X": 91,
                "Y": -0.5752597372915398
            },
            {
                "X": 92,
                "Y": -0.36895322428228167
            },
            {
                "X": 93,
                "Y": 0.7657482455755041
            },
            {
                "X": 94,
                "Y": -1.1006615868256642
            },
            {
                "X": 95,
                "Y": 0.7338296604406034
            },
            {
                "X": 96,
                "Y": -0.03157402215285636
            },
            {
                "X": 97,
                "Y": -1.2739418607470343
            },
            {
                "X": 98,
                "Y": 10.065816275526934
            },
            {
                "X": 99,
                "Y": -0.5425151791589167
            },
            {
                "X": 100,
                "Y": 4.075466725531909
            },
            {
                "X": 101,
                "Y": -0.7757206526918475
            },
            {
                "X": 102,
                "Y": -0.12322816490315489
            },
            {
                "X": 103,
                "Y": 7.677604462815123
            },
            {
                "X": 104,
                "Y": 0.1653734061807222
            },
            {
                "X": 105,
                "Y": 0.8998557207587011
            },
            {
                "X": 106,
                "Y": 1.2571959907558432
            },
            {
                "X": 107,
                "Y": 1.1540686067101387
            },
            {
                "X": 108,
                "Y": -0.674225800989242
            },
            {
                "X": 109,
                "Y": 0.8832666713317444
            },
            {
                "X": 110,
                "Y": -1.8007409988365144
            },
            {
                "X": 111,
                "Y": 0.3155240212907322
            },
            {
                "X": 112,
                "Y": -0.2989424331214217
            },
            {
                "X": 113,
                "Y": 0.9232667061538622
            },
            {
                "X": 114,
                "Y": -0.8646104231287141
            },
            {
                "X": 115,
                "Y": 0.9063238957912969
            },
            {
                "X": 116,
                "Y": 0.1436653653338619
            },
            {
                "X": 117,
                "Y": -0.4287840376303047
            },
            {
                "X": 118,
                "Y": 0.043633485845887915
            },
            {
                "X": 119,
                "Y": -1.1596301258930446
            },
            {
                "X": 120,
                "Y": 6.970081590572216
            },
            {
                "X": 121,
                "Y": 1.0626972062745461
            },
            {
                "X": 122,
                "Y": 10.240867646874538
            },
            {
                "X": 123,
                "Y": 0.8904773090910271
            },
            {
                "X": 124,
                "Y": 0.11018472952624332
            },
            {
                "X": 125,
                "Y": -0.280878365152031
            },
            {
                "X": 126,
                "Y": 0.4708767786979145
            },
            {
                "X": 127,
                "Y": -0.12265481194605361
            },
            {
                "X": 128,
                "Y": 1.8097161228067284
            },
            {
                "X": 129,
                "Y": 7.395100789615601
            },
            {
                "X": 130,
                "Y": -0.10491641792539533
            },
            {
                "X": 131,
                "Y": 0.5600092990119518
            },
            {
                "X": 132,
                "Y": -1.1794564037301838
            },
            {
                "X": 133,
                "Y": -0.4678037812617453
            },
            {
                "X": 134,
                "Y": -1.742413192457269
            },
            {
                "X": 135,
                "Y": 5.640323873009933
            },
            {
                "X": 136,
                "Y": -2.170067190083364
            },
            {
                "X": 137,
                "Y": 0.42451004910174395
            },
            {
                "X": 138,
                "Y": 0.14647863881476825
            },
            {
                "X": 139,
                "Y": 0.059274440711844824
            },
            {
                "X": 140,
                "Y": -0.4912539266891554
            },
            {
                "X": 141,
                "Y": -1.0171730821238116
            },
            {
                "X": 142,
                "Y": 0.41930719619987455
            },
            {
                "X": 143,
                "Y": -0.7713675081404654
            },
            {
                "X": 144,
                "Y": 1.437886515078047
            },
            {
                "X": 145,
                "Y": 2.686767122992888
            },
            {
                "X": 146,
                "Y": 0.396732881726082
            },
            {
                "X": 147,
                "Y": 0.4769239605519288
            },
            {
                "X": 148,
                "Y": 0.8159016972464805
            },
            {
                "X": 149,
                "Y": -0.5030922177285254
            },
            {
                "X": 150,
                "Y": 0.14486419601472417
            },
            {
                "X": 151,
                "Y": 0.03915844904537185
            },
            {
                "X": 152,
                "Y": 7.499991261290018
            },
            {
                "X": 153,
                "Y": 8.602875204815554
            },
            {
                "X": 154,
                "Y": 0.9768648480137673
            },
            {
                "X": 155,
                "Y": -0.6309415224928188
            },
            {
                "X": 156,
                "Y": -0.8386027200679316
            },
            {
                "X": 157,
                "Y": -0.4392036626361821
            },
            {
                "X": 158,
                "Y": -1.3645267902345468
            },
            {
                "X": 159,
                "Y": -1.2723711422064257
            },
            {
                "X": 160,
                "Y": 0.8601908877225237
            },
            {
                "X": 161,
                "Y": 10.83486567894394
            },
            {
                "X": 162,
                "Y": -0.712860144830928
            },
            {
                "X": 163,
                "Y": 7.675661410137967
            },
            {
                "X": 164,
                "Y": 10.254981781735895
            },
            {
                "X": 165,
                "Y": -0.4982101249605294
            },
            {
                "X": 166,
                "Y": 1.670691069540805
            },
            {
                "X": 167,
                "Y": 0.43176528013807924
            },
            {
                "X": 168,
                "Y": 0.426712047341392
            },
            {
                "X": 169,
                "Y": 0.9867459860375951
            },
            {
                "X": 170,
                "Y": 0.9776806028402802
            },
            {
                "X": 171,
                "Y": -1.0646682013429372
            },
            {
                "X": 172,
                "Y": 0.5388479400375095
            },
            {
                "X": 173,
                "Y": 0.8430825685885635
            },
            {
                "X": 174,
                "Y": 0.9007229056305692
            },
            {
                "X": 175,
                "Y": 8.345367348157264
            },
            {
                "X": 176,
                "Y": 0.4871308124535103
            },
            {
                "X": 177,
                "Y": -0.3583995873288774
            },
            {
                "X": 178,
                "Y": 1.202976753010021
            },
            {
                "X": 179,
                "Y": 0.45869919719676394
            },
            {
                "X": 180,
                "Y": -1.119630815883547
            },
            {
                "X": 181,
                "Y": 0.3351303980556235
            },
            {
                "X": 182,
                "Y": -0.68690022046664
            },
            {
                "X": 183,
                "Y": 1.2068168153505552
            },
            {
                "X": 184,
                "Y": 1.9175210593909267
            },
            {
                "X": 185,
                "Y": 0.5421989560792255
            },
            {
                "X": 186,
                "Y": 0.7223535548455531
            },
            {
                "X": 187,
                "Y": -0.174881350251276
            },
            {
                "X": 188,
                "Y": -0.11599682391072164
            },
            {
                "X": 189,
                "Y": -1.9871268314958257
            },
            {
                "X": 190,
                "Y": 0.009982921154422253
            },
            {
                "X": 191,
                "Y": 0.07121491979349509
            },
            {
                "X": 192,
                "Y": 7.258344190736789
            },
            {
                "X": 193,
                "Y": 0.5544383768007635
            },
            {
                "X": 194,
                "Y": 0.2745458467246506
            },
            {
                "X": 195,
                "Y": 1.720705079412357
            },
            {
                "X": 196,
                "Y": -2.3942127640134743
            },
            {
                "X": 197,
                "Y": 4.949572010430324
            },
            {
                "X": 198,
                "Y": 1.2219812466894533
            },
            {
                "X": 199,
                "Y": 0.37437698790786034
            },
            {
                "X": 200,
                "Y": -1.3810042562110136
            },
            {
                "X": 201,
                "Y": -0.6766865526798402
            },
            {
                "X": 202,
                "Y": 0.40759191728976685
            },
            {
                "X": 203,
                "Y": 0.5936197708627151
            },
            {
                "X": 204,
                "Y": 0.7836184213324792
            },
            {
                "X": 205,
                "Y": 0.6730021133331473
            },
            {
                "X": 206,
                "Y": 0.4787814331545838
            },
            {
                "X": 207,
                "Y": 0.8390401156311827
            },
            {
                "X": 208,
                "Y": 0.8691237159058469
            },
            {
                "X": 209,
                "Y": 1.3463277348388478
            },
            {
                "X": 210,
                "Y": 1.3673476888584215
            },
            {
                "X": 211,
                "Y": 0.366827391789123
            },
            {
                "X": 212,
                "Y": 5.546348762609134
            },
            {
                "X": 213,
                "Y": 0.6669450234452535
            },
            {
                "X": 214,
                "Y": -1.1453648316957603
            },
            {
                "X": 215,
                "Y": 0.4388914530350147
            },
            {
                "X": 216,
                "Y": -0.4378447132113028
            },
            {
                "X": 217,
                "Y": -0.4656897764771673
            },
            {
                "X": 218,
                "Y": 8.269766675738591
            },
            {
                "X": 219,
                "Y": -0.8195223120459204
            },
            {
                "X": 220,
                "Y": 0.7588538681327697
            },
            {
                "X": 221,
                "Y": 0.5180565310281622
            },
            {
                "X": 222,
                "Y": 0.42819690615840467
            },
            {
                "X": 223,
                "Y": 0.20813500786595626
            },
            {
                "X": 224,
                "Y": 9.734145601680092
            },
            {
                "X": 225,
                "Y": 10.927417826143436
            },
            {
                "X": 226,
                "Y": 0.7349767205139115
            },
            {
                "X": 227,
                "Y": -0.5932387904547273
            },
            {
                "X": 228,
                "Y": 1.5240641786379931
            },
            {
                "X": 229,
                "Y": 1.216460345032035
            },
            {
                "X": 230,
                "Y": 1.0583691675621811
            },
            {
                "X": 231,
                "Y": -0.5168908558731443
            },
            {
                "X": 232,
                "Y": 1.0808539099471925
            },
            {
                "X": 233,
                "Y": -1.3828403783429593
            },
            {
                "X": 234,
                "Y": 0.10645635191534848
            },
            {
                "X": 235,
                "Y": 0.274257861387587
            },
            {
                "X": 236,
                "Y": 3.5787282976825887
            },
            {
                "X": 237,
                "Y": 0.9941209584617531
            },
            {
                "X": 238,
                "Y": -1.3607070212341486
            },
            {
                "X": 239,
                "Y": -0.34612857182479767
            },
            {
                "X": 240,
                "Y": 11.232109706798875
            },
            {
                "X": 241,
                "Y": 0.6364084377582877
            },
            {
                "X": 242,
                "Y": -0.21365563167928872
            },
            {
                "X": 243,
                "Y": -0.5300287107636138
            },
            {
                "X": 244,
                "Y": -1.1473955214281615
            },
            {
                "X": 245,
                "Y": -1.3310203451753655
            },
            {
                "X": 246,
                "Y": 0.8671129451504812
            },
            {
                "X": 247,
                "Y": 0.10177722240358543
            },
            {
                "X": 248,
                "Y": -0.5654217995788452
            },
            {
                "X": 249,
                "Y": 0.5448665493967713
            },
            {
                "X": 250,
                "Y": -0.5882167516066237
            },
            {
                "X": 251,
                "Y": 4.241315171680358
            },
            {
                "X": 252,
                "Y": -1.0551008282559304
            },
            {
                "X": 253,
                "Y": 1.2310259051114596
            },
            {
                "X": 254,
                "Y": 1.49268411812202
            },
            {
                "X": 255,
                "Y": 1.095726930187904
            },
            {
                "X": 256,
                "Y": -0.8327542585964425
            },
            {
                "X": 257,
                "Y": 1.4211968363592418
            },
            {
                "X": 258,
                "Y": -0.5192583585933712
            },
            {
                "X": 259,
                "Y": 5.208640040213326
            },
            {
                "X": 260,
                "Y": 2.065874698943237
            },
            {
                "X": 261,
                "Y": 10.063128201909691
            },
            {
                "X": 262,
                "Y": 0.17836787921249603
            },
            {
                "X": 263,
                "Y": 1.2095959584703142
            },
            {
                "X": 264,
                "Y": 2.0522805725436952
            },
            {
                "X": 265,
                "Y": 1.1729834035917894
            },
            {
                "X": 266,
                "Y": -0.29920925397489834
            },
            {
                "X": 267,
                "Y": 1.5449105972835584
            },
            {
                "X": 268,
                "Y": 0.5132883538886516
            },
            {
                "X": 269,
                "Y": -0.47030417336944247
            },
            {
                "X": 270,
                "Y": -0.31009708986219864
            },
            {
                "X": 271,
                "Y": -0.4280439348972683
            },
            {
                "X": 272,
                "Y": -1.407237887232027
            },
            {
                "X": 273,
                "Y": -0.7965903628109772
            },
            {
                "X": 274,
                "Y": -0.8856434893108032
            },
            {
                "X": 275,
                "Y": 2.1106337088932907
            },
            {
                "X": 276,
                "Y": 1.0703925335996451
            },
            {
                "X": 277,
                "Y": 1.3994529188982727
            },
            {
                "X": 278,
                "Y": 0.571403123013241
            },
            {
                "X": 279,
                "Y": 0.2754305320881706
            },
            {
                "X": 280,
                "Y": -0.19925300342756852
            },
            {
                "X": 281,
                "Y": -0.359019207259414
            },
            {
                "X": 282,
                "Y": 0.12660968200395628
            },
            {
                "X": 283,
                "Y": -1.6923342767808864
            },
            {
                "X": 284,
                "Y": 1.3371478004567898
            },
            {
                "X": 285,
                "Y": -1.107167693436488
            },
            {
                "X": 286,
                "Y": -0.5722479926065639
            },
            {
                "X": 287,
                "Y": 0.8971525284923286
            },
            {
                "X": 288,
                "Y": 6.982003987937573
            },
            {
                "X": 289,
                "Y": -1.8990241808524702
            },
            {
                "X": 290,
                "Y": -1.7826868026732061
            },
            {
                "X": 291,
                "Y": -0.282853143137324
            },
            {
                "X": 292,
                "Y": -0.4487578974476542
            },
            {
                "X": 293,
                "Y": 11.121017981372951
            },
            {
                "X": 294,
                "Y": -0.9810864213288608
            },
            {
                "X": 295,
                "Y": -1.4348601372214884
            },
            {
                "X": 296,
                "Y": -0.7536267389335919
            },
            {
                "X": 297,
                "Y": 1.3750592334440004
            },
            {
                "X": 298,
                "Y": 0.0065116301759978144
            },
            {
                "X": 299,
                "Y": -0.5379011880554769
            },
            {
                "X": 300,
                "Y": 0.49367070962784493
            },
            {
                "X": 301,
                "Y": -0.8274773000175109
            },
            {
                "X": 302,
                "Y": 0.22103084414900265
            },
            {
                "X": 303,
                "Y": -0.5269785848661535
            },
            {
                "X": 304,
                "Y": -0.40056693239064695
            },
            {
                "X": 305,
                "Y": -0.4596914120042506
            },
            {
                "X": 306,
                "Y": 3.5855874292978225
            },
            {
                "X": 307,
                "Y": 0.5194943306065428
            },
            {
                "X": 308,
                "Y": -1.7775381565743593
            },
            {
                "X": 309,
                "Y": -0.28985866278330663
            },
            {
                "X": 310,
                "Y": 0.3678982966386156
            },
            {
                "X": 311,
                "Y": 0.9631750262227665
            },
            {
                "X": 312,
                "Y": -0.4511565183861271
            },
            {
                "X": 313,
                "Y": -0.14389093339637957
            },
            {
                "X": 314,
                "Y": -0.6476004229042642
            },
            {
                "X": 315,
                "Y": 0.7696970091299896
            },
            {
                "X": 316,
                "Y": -1.2993041638893728
            },
            {
                "X": 317,
                "Y": 0.7552073675038515
            },
            {
                "X": 318,
                "Y": 0.1291582945915735
            },
            {
                "X": 319,
                "Y": 1.121527244756875
            },
            {
                "X": 320,
                "Y": 5.597323823006663
            },
            {
                "X": 321,
                "Y": 6.885576203716484
            },
            {
                "X": 322,
                "Y": 1.2417081570957715
            },
            {
                "X": 323,
                "Y": 0.9914682807805609
            },
            {
                "X": 324,
                "Y": -1.043315907126984
            },
            {
                "X": 325,
                "Y": 0.432159353809249
            },
            {
                "X": 326,
                "Y": 0.06538117388296354
            },
            {
                "X": 327,
                "Y": -0.7009678756670047
            },
            {
                "X": 328,
                "Y": -0.7440713482438635
            },
            {
                "X": 329,
                "Y": 1.0592236357423397
            },
            {
                "X": 330,
                "Y": 1.271145094848778
            },
            {
                "X": 331,
                "Y": 0.25012077286920686
            },
            {
                "X": 332,
                "Y": -1.6477955081624134
            },
            {
                "X": 333,
                "Y": -0.8003449005843677
            },
            {
                "X": 334,
                "Y": 6.004011199182836
            },
            {
                "X": 335,
                "Y": -0.41983601978920576
            },
            {
                "X": 336,
                "Y": -0.23007396265793634
            },
            {
                "X": 337,
                "Y": 1.6625866758331398
            },
            {
                "X": 338,
                "Y": 0.9007105756996845
            },
            {
                "X": 339,
                "Y": 0.11116860259039031
            },
            {
                "X": 340,
                "Y": -0.3882626276898919
            },
            {
                "X": 341,
                "Y": 0.010639884378650013
            },
            {
                "X": 342,
                "Y": 1.069589911947667
            },
            {
                "X": 343,
                "Y": -1.6015099163839503
            },
            {
                "X": 344,
                "Y": 0.6530575354076154
            },
            {
                "X": 345,
                "Y": 0.28996250808107304
            },
            {
                "X": 346,
                "Y": -0.3054229395267626
            },
            {
                "X": 347,
                "Y": -1.942912429253986
            },
            {
                "X": 348,
                "Y": -0.1687327690886736
            },
            {
                "X": 349,
                "Y": 0.7968301948978586
            },
            {
                "X": 350,
                "Y": -0.707398030362808
            },
            {
                "X": 351,
                "Y": -0.19720313020059388
            },
            {
                "X": 352,
                "Y": -1.1335500674934336
            },
            {
                "X": 353,
                "Y": 0.7694784445425421
            },
            {
                "X": 354,
                "Y": -0.8534946251873129
            },
            {
                "X": 355,
                "Y": 0.33384645025307735
            },
            {
                "X": 356,
                "Y": 0.2700627594559517
            },
            {
                "X": 357,
                "Y": 7.500459186989473
            },
            {
                "X": 358,
                "Y": 0.7114622943981991
            },
            {
                "X": 359,
                "Y": 0.11456758696675991
            },
            {
                "X": 360,
                "Y": 4.2736251707866595
            },
            {
                "X": 361,
                "Y": -2.076527273363092
            },
            {
                "X": 362,
                "Y": 1.2292824311618638
            },
            {
                "X": 363,
                "Y": -1.2454640599181717
            },
            {
                "X": 364,
                "Y": 0.17160965479197837
            },
            {
                "X": 365,
                "Y": 0.5451826630519981
            },
            {
                "X": 366,
                "Y": -0.829044308421462
            },
            {
                "X": 367,
                "Y": 0.4854658651693279
            },
            {
                "X": 368,
                "Y": -0.5917472038004145
            },
            {
                "X": 369,
                "Y": 0.3973910330645778
            },
            {
                "X": 370,
                "Y": -0.19482622938486693
            },
            {
                "X": 371,
                "Y": -2.4118705518860226
            },
            {
                "X": 372,
                "Y": -0.637980810496346
            },
            {
                "X": 373,
                "Y": 0.01186076299049161
            },
            {
                "X": 374,
                "Y": -0.9421323925626642
            },
            {
                "X": 375,
                "Y": 0.26146609637848883
            },
            {
                "X": 376,
                "Y": -0.5830334834164562
            },
            {
                "X": 377,
                "Y": -0.09297886520648792
            },
            {
                "X": 378,
                "Y": -1.1253001325540646
            },
            {
                "X": 379,
                "Y": 0.5957080569845736
            },
            {
                "X": 380,
                "Y": -1.591370631906483
            },
            {
                "X": 381,
                "Y": 6.096965948647802
            },
            {
                "X": 382,
                "Y": -0.1189314939176055
            },
            {
                "X": 383,
                "Y": -3.019873113256506
            },
            {
                "X": 384,
                "Y": 1.918571845120937
            },
            {
                "X": 385,
                "Y": 0.9112435442751836
            },
            {
                "X": 386,
                "Y": -0.22753322081358715
            },
            {
                "X": 387,
                "Y": 0.5693586723715396
            },
            {
                "X": 388,
                "Y": -0.9314125297044623
            },
            {
                "X": 389,
                "Y": 0.7290850809631251
            },
            {
                "X": 390,
                "Y": 0.8636124351923792
            },
            {
                "X": 391,
                "Y": 1.5672468708032288
            },
            {
                "X": 392,
                "Y": 0.8364109640466004
            },
            {
                "X": 393,
                "Y": -0.25045237050732
            },
            {
                "X": 394,
                "Y": -0.15650978900104687
            },
            {
                "X": 395,
                "Y": 6.835294258271108
            },
            {
                "X": 396,
                "Y": 0.8771210776654191
            },
            {
                "X": 397,
                "Y": 0.6199632748794501
            },
            {
                "X": 398,
                "Y": -0.4668680218045168
            },
            {
                "X": 399,
                "Y": -0.5671277268115712
            },
            {
                "X": 400,
                "Y": 0.6855032093078977
            },
            {
                "X": 401,
                "Y": -0.3752309873507288
            },
            {
                "X": 402,
                "Y": 0.8043008578855484
            },
            {
                "X": 403,
                "Y": -1.3716989604104746
            },
            {
                "X": 404,
                "Y": -1.7018340426269976
            },
            {
                "X": 405,
                "Y": -1.6187726490716927
            },
            {
                "X": 406,
                "Y": 0.038435347783258876
            },
            {
                "X": 407,
                "Y": -1.7047881322281992
            },
            {
                "X": 408,
                "Y": 6.024881937528374
            },
            {
                "X": 409,
                "Y": 10.281131719101202
            },
            {
                "X": 410,
                "Y": -0.25151708969684405
            },
            {
                "X": 411,
                "Y": -0.9127607423229376
            },
            {
                "X": 412,
                "Y": 7.412423190746969
            },
            {
                "X": 413,
                "Y": -0.9483880828885867
            },
            {
                "X": 414,
                "Y": 1.0072769933259824
            },
            {
                "X": 415,
                "Y": -1.2581032695582808
            },
            {
                "X": 416,
                "Y": 0.22315161121793606
            },
            {
                "X": 417,
                "Y": -1.9840702596018283
            },
            {
                "X": 418,
                "Y": -1.4629379647824245
            },
            {
                "X": 419,
                "Y": 0.49553402019548415
            },
            {
                "X": 420,
                "Y": 1.8781287757115153
            },
            {
                "X": 421,
                "Y": 0.14930355543114857
            },
            {
                "X": 422,
                "Y": 0.6815194723321369
            },
            {
                "X": 423,
                "Y": 0.3814774386765099
            },
            {
                "X": 424,
                "Y": 1.9092748081965496
            },
            {
                "X": 425,
                "Y": -0.5086909719217844
            },
            {
                "X": 426,
                "Y": 0.0859890550613849
            },
            {
                "X": 427,
                "Y": 0.6470405675144619
            },
            {
                "X": 428,
                "Y": -1.4383314271618501
            },
            {
                "X": 429,
                "Y": -0.08314974674885678
            },
            {
                "X": 430,
                "Y": -0.7661849625345643
            },
            {
                "X": 431,
                "Y": 0.35343086744273444
            },
            {
                "X": 432,
                "Y": 6.1204789762268605
            },
            {
                "X": 433,
                "Y": -1.4376372139323947
            },
            {
                "X": 434,
                "Y": 0.8869501244383189
            },
            {
                "X": 435,
                "Y": -0.9426298917495172
            },
            {
                "X": 436,
                "Y": -0.380684811632916
            },
            {
                "X": 437,
                "Y": 0.8323465232603081
            },
            {
                "X": 438,
                "Y": -1.1655027412319243
            },
            {
                "X": 439,
                "Y": -0.6141045919534227
            },
            {
                "X": 440,
                "Y": -0.8263040211552045
            },
            {
                "X": 441,
                "Y": -0.7147216411788242
            },
            {
                "X": 442,
                "Y": -0.09508853720703528
            },
            {
                "X": 443,
                "Y": -0.6636630372247879
            },
            {
                "X": 444,
                "Y": 7.627217931864948
            },
            {
                "X": 445,
                "Y": -0.4996482654029704
            },
            {
                "X": 446,
                "Y": 1.2487135614285882
            },
            {
                "X": 447,
                "Y": 0.2920612625199013
            },
            {
                "X": 448,
                "Y": 10.414538986854149
            },
            {
                "X": 449,
                "Y": 0.8449991899994848
            },
            {
                "X": 450,
                "Y": 8.316965254411246
            },
            {
                "X": 451,
                "Y": 0.6323824469981902
            },
            {
                "X": 452,
                "Y": 1.048340985633042
            },
            {
                "X": 453,
                "Y": 0.40440590947688376
            },
            {
                "X": 454,
                "Y": 0.014531178712017104
            },
            {
                "X": 455,
                "Y": -0.12133969212660291
            },
            {
                "X": 456,
                "Y": -0.5307393782452215
            },
            {
                "X": 457,
                "Y": -0.545605545979062
            },
            {
                "X": 458,
                "Y": 2.7210460988969207
            },
            {
                "X": 459,
                "Y": -1.6906295754750538
            },
            {
                "X": 460,
                "Y": -1.9515305817576003
            },
            {
                "X": 461,
                "Y": 0.6436565635559136
            },
            {
                "X": 462,
                "Y": -0.32495780482585074
            },
            {
                "X": 463,
                "Y": -0.675594480417698
            },
            {
                "X": 464,
                "Y": 0.6667696547122389
            },
            {
                "X": 465,
                "Y": 0.04249921432231729
            },
            {
                "X": 466,
                "Y": -0.9018476006328181
            },
            {
                "X": 467,
                "Y": 6.602966566001819
            },
            {
                "X": 468,
                "Y": -0.9239032461827733
            },
            {
                "X": 469,
                "Y": -0.46829111222506775
            },
            {
                "X": 470,
                "Y": -1.0167679491930786
            },
            {
                "X": 471,
                "Y": 6.574092963161425
            },
            {
                "X": 472,
                "Y": 0.0718477077528719
            },
            {
                "X": 473,
                "Y": -0.9481106700866619
            },
            {
                "X": 474,
                "Y": 6.900663419736139
            },
            {
                "X": 475,
                "Y": -1.2707279749666263
            },
            {
                "X": 476,
                "Y": -1.3980891324926359
            },
            {
                "X": 477,
                "Y": -0.28399277161003295
            },
            {
                "X": 478,
                "Y": 0.7121154551238483
            },
            {
                "X": 479,
                "Y": 0.0017521322198501092
            },
            {
                "X": 480,
                "Y": 5.1325475651495305
            },
            {
                "X": 481,
                "Y": 8.620572862608617
            },
            {
                "X": 482,
                "Y": 0.540076187387077
            },
            {
                "X": 483,
                "Y": -0.6117109701111496
            },
            {
                "X": 484,
                "Y": 2.130236293228213
            },
            {
                "X": 485,
                "Y": 0.21453011107778722
            },
            {
                "X": 486,
                "Y": -0.42295490550402415
            },
            {
                "X": 487,
                "Y": 1.0109378173805585
            },
            {
                "X": 488,
                "Y": -0.7315130244027654
            },
            {
                "X": 489,
                "Y": -0.06365370779878406
            },
            {
                "X": 490,
                "Y": -1.9495370164525851
            },
            {
                "X": 491,
                "Y": -1.0931198254724126
            },
            {
                "X": 492,
                "Y": 0.43410658129238827
            },
            {
                "X": 493,
                "Y": -0.853923597127161
            },
            {
                "X": 494,
                "Y": 0.28039659795135147
            },
            {
                "X": 495,
                "Y": -1.1488526457008668
            },
            {
                "X": 496,
                "Y": 6.69828446022596
            },
            {
                "X": 497,
                "Y": 0.39007662202461124
            },
            {
                "X": 498,
                "Y": 0.11408046140886216
            },
            {
                "X": 499,
                "Y": 1.6593613358126824
            },
            {
                "X": 500,
                "Y": 0.6472987697612983
            },
            {
                "X": 501,
                "Y": 0.33777929629245373
            },
            {
                "X": 502,
                "Y": 0.3977815727051445
            },
            {
                "X": 503,
                "Y": 0.0889377835644531
            },
            {
                "X": 504,
                "Y": -1.4053143825393164
            },
            {
                "X": 505,
                "Y": 0.4703431261194948
            },
            {
                "X": 506,
                "Y": -0.1767631141283188
            },
            {
                "X": 507,
                "Y": 0.28519181420655415
            },
            {
                "X": 508,
                "Y": 2.198675299267545
            },
            {
                "X": 509,
                "Y": 4.850143439905433
            },
            {
                "X": 510,
                "Y": 0.36206509664775705
            },
            {
                "X": 511,
                "Y": -0.45701572409350083
            },
            {
                "X": 512,
                "Y": 0.8437034721114018
            },
            {
                "X": 513,
                "Y": -0.23258421766567372
            },
            {
                "X": 514,
                "Y": -0.4383647369293772
            },
            {
                "X": 515,
                "Y": -1.3910022313949881
            },
            {
                "X": 516,
                "Y": 0.7403444155197347
            },
            {
                "X": 517,
                "Y": -0.8925209735897429
            },
            {
                "X": 518,
                "Y": 0.4476536635736289
            },
            {
                "X": 519,
                "Y": 8.603042628518976
            },
            {
                "X": 520,
                "Y": 0.3141573410518516
            },
            {
                "X": 521,
                "Y": 0.38424856087302917
            },
            {
                "X": 522,
                "Y": -0.07204857844647015
            },
            {
                "X": 523,
                "Y": 0.4293101376820167
            },
            {
                "X": 524,
                "Y": -1.0680653839010008
            },
            {
                "X": 525,
                "Y": 0.9581918265938274
            },
            {
                "X": 526,
                "Y": 1.5281034932491253
            },
            {
                "X": 527,
                "Y": 0.07076384951386853
            },
            {
                "X": 528,
                "Y": -0.38002048892250545
            },
            {
                "X": 529,
                "Y": 5.790980891770339
            },
            {
                "X": 530,
                "Y": -0.4276687655128216
            },
            {
                "X": 531,
                "Y": 0.3011942355848933
            },
            {
                "X": 532,
                "Y": -0.10279420004499057
            },
            {
                "X": 533,
                "Y": 0.3455397750207074
            },
            {
                "X": 534,
                "Y": 0.5098794764238288
            },
            {
                "X": 535,
                "Y": 0.09747834928057604
            },
            {
                "X": 536,
                "Y": 1.2848961478148786
            },
            {
                "X": 537,
                "Y": -0.8950123810252965
            },
            {
                "X": 538,
                "Y": -0.21906270542678427
            },
            {
                "X": 539,
                "Y": -1.342887204630796
            },
            {
                "X": 540,
                "Y": -0.00869533165591799
            },
            {
                "X": 541,
                "Y": -0.49268156928634804
            },
            {
                "X": 542,
                "Y": 0.39796128586513213
            },
            {
                "X": 543,
                "Y": -0.07996836602968829
            },
            {
                "X": 544,
                "Y": 0.6979690785767433
            },
            {
                "X": 545,
                "Y": 0.1599868626541674
            },
            {
                "X": 546,
                "Y": -1.1630988982868882
            },
            {
                "X": 547,
                "Y": -0.46435642618601664
            },
            {
                "X": 548,
                "Y": -0.8318170128001581
            },
            {
                "X": 549,
                "Y": -1.4432151588538278
            },
            {
                "X": 550,
                "Y": -0.18477064307737856
            },
            {
                "X": 551,
                "Y": -0.2562428611420812
            },
            {
                "X": 552,
                "Y": 0.7164929033912337
            },
            {
                "X": 553,
                "Y": -1.5655565048272
            },
            {
                "X": 554,
                "Y": -0.8967764317696786
            },
            {
                "X": 555,
                "Y": 1.0062301962796105
            },
            {
                "X": 556,
                "Y": 0.2227675134180976
            },
            {
                "X": 557,
                "Y": 0.4654002468466707
            },
            {
                "X": 558,
                "Y": -0.7544782083928798
            },
            {
                "X": 559,
                "Y": 0.78310125933767
            },
            {
                "X": 560,
                "Y": 0.8670854467676978
            },
            {
                "X": 561,
                "Y": 5.54722658790993
            },
            {
                "X": 562,
                "Y": -1.198200977893634
            },
            {
                "X": 563,
                "Y": -0.5809358336785777
            },
            {
                "X": 564,
                "Y": 0.11877805744774739
            },
            {
                "X": 565,
                "Y": 1.6602865446377149
            },
            {
                "X": 566,
                "Y": 6.518090026999346
            },
            {
                "X": 567,
                "Y": 0.10222099458217947
            },
            {
                "X": 568,
                "Y": -0.5263474262778952
            },
            {
                "X": 569,
                "Y": -1.3114471066916276
            },
            {
                "X": 570,
                "Y": 0.4767139969217982
            },
            {
                "X": 571,
                "Y": 0.2083474810235818
            },
            {
                "X": 572,
                "Y": -0.6079486012473069
            },
            {
                "X": 573,
                "Y": 0.37251760860243116
            },
            {
                "X": 574,
                "Y": 8.016560860013492
            },
            {
                "X": 575,
                "Y": -0.6855207618445314
            },
            {
                "X": 576,
                "Y": -0.5560272975101174
            },
            {
                "X": 577,
                "Y": 7.660128370446337
            },
            {
                "X": 578,
                "Y": -1.158500708111979
            },
            {
                "X": 579,
                "Y": -0.9853627455062973
            },
            {
                "X": 580,
                "Y": 1.7327718789511957
            },
            {
                "X": 581,
                "Y": -1.3073976622795747
            },
            {
                "X": 582,
                "Y": 1.3826126696552161
            },
            {
                "X": 583,
                "Y": 7.9622721910213485
            },
            {
                "X": 584,
                "Y": 1.8431603372494345
            },
            {
                "X": 585,
                "Y": -0.7222015869459414
            },
            {
                "X": 586,
                "Y": -0.7126197562748814
            },
            {
                "X": 587,
                "Y": -1.9753918726645128
            },
            {
                "X": 588,
                "Y": 0.4131818799808685
            },
            {
                "X": 589,
                "Y": 0.6636465284525935
            },
            {
                "X": 590,
                "Y": 5.763468099538693
            },
            {
                "X": 591,
                "Y": -0.6201848685438125
            },
            {
                "X": 592,
                "Y": -0.047440701194890474
            },
            {
                "X": 593,
                "Y": 1.2074212418334154
            },
            {
                "X": 594,
                "Y": -0.18797636624846592
            },
            {
                "X": 595,
                "Y": 0.8177817275832976
            },
            {
                "X": 596,
                "Y": -0.7322805966765037
            },
            {
                "X": 597,
                "Y": -0.2148165654960405
            },
            {
                "X": 598,
                "Y": 0.6200637935775719
            },
            {
                "X": 599,
                "Y": 1.1009333034983178
            },
            {
                "X": 600,
                "Y": 6.945537491913985
            },
            {
                "X": 601,
                "Y": -0.18800517110472031
            },
            {
                "X": 602,
                "Y": 1.547239521970351
            },
            {
                "X": 603,
                "Y": 1.5576059032235023
            },
            {
                "X": 604,
                "Y": 1.0307130954352035
            },
            {
                "X": 605,
                "Y": 0.6761496574869311
            },
            {
                "X": 606,
                "Y": -0.4805140058159509
            },
            {
                "X": 607,
                "Y": 0.14246522284606372
            },
            {
                "X": 608,
                "Y": -1.349313112324087
            },
            {
                "X": 609,
                "Y": 0.26190006753548856
            },
            {
                "X": 610,
                "Y": -0.2372367241031463
            },
            {
                "X": 611,
                "Y": 1.3073711729893205
            },
            {
                "X": 612,
                "Y": -0.5313807424059529
            },
            {
                "X": 613,
                "Y": 1.9013732943293984
            },
            {
                "X": 614,
                "Y": -0.4243222545675117
            },
            {
                "X": 615,
                "Y": 0.3439856192948347
            },
            {
                "X": 616,
                "Y": 9.274081191957647
            },
            {
                "X": 617,
                "Y": 0.6508929936332276
            },
            {
                "X": 618,
                "Y": 1.2943315030810134
            },
            {
                "X": 619,
                "Y": -0.5857350084852497
            },
            {
                "X": 620,
                "Y": 0.2955091248021928
            },
            {
                "X": 621,
                "Y": -0.5320726590633457
            },
            {
                "X": 622,
                "Y": 0.48636976489084965
            },
            {
                "X": 623,
                "Y": 0.009204398631488152
            },
            {
                "X": 624,
                "Y": -0.3364350328080358
            },
            {
                "X": 625,
                "Y": -1.8816652549764106
            },
            {
                "X": 626,
                "Y": 2.675636456906882
            },
            {
                "X": 627,
                "Y": -0.562085978071423
            },
            {
                "X": 628,
                "Y": -0.3821820243197738
            },
            {
                "X": 629,
                "Y": -1.2160800566627978
            },
            {
                "X": 630,
                "Y": -0.22156271764294908
            },
            {
                "X": 631,
                "Y": 0.8409611045472108
            },
            {
                "X": 632,
                "Y": -0.17575517650232592
            },
            {
                "X": 633,
                "Y": -1.899165316846202
            },
            {
                "X": 634,
                "Y": 1.0036735870174194
            },
            {
                "X": 635,
                "Y": 0.9320061537459261
            },
            {
                "X": 636,
                "Y": 0.28434917057807574
            },
            {
                "X": 637,
                "Y": 8.05694965817355
            },
            {
                "X": 638,
                "Y": -0.7024531066954965
            },
            {
                "X": 639,
                "Y": -1.5238018137780849
            },
            {
                "X": 640,
                "Y": -0.14216570029038558
            },
            {
                "X": 641,
                "Y": -2.632033838618061
            },
            {
                "X": 642,
                "Y": -0.100458479874691
            },
            {
                "X": 643,
                "Y": -1.0871611041078624
            },
            {
                "X": 644,
                "Y": -1.5757115413580831
            },
            {
                "X": 645,
                "Y": -0.0010862822419499113
            },
            {
                "X": 646,
                "Y": 0.19815269310144518
            },
            {
                "X": 647,
                "Y": 6.42369800861424
            },
            {
                "X": 648,
                "Y": 1.0034205164702195
            },
            {
                "X": 649,
                "Y": 1.5825593832360307
            },
            {
                "X": 650,
                "Y": -0.5106097827665416
            },
            {
                "X": 651,
                "Y": -0.907406738372165
            },
            {
                "X": 652,
                "Y": -1.8499761177378429
            },
            {
                "X": 653,
                "Y": -0.559984993042486
            },
            {
                "X": 654,
                "Y": 7.12876633457538
            },
            {
                "X": 655,
                "Y": 0.6553454883628334
            },
            {
                "X": 656,
                "Y": 0.04506847007261385
            },
            {
                "X": 657,
                "Y": 0.9718899604653355
            },
            {
                "X": 658,
                "Y": -0.843467611069525
            },
            {
                "X": 659,
                "Y": 6.306260718999536
            },
            {
                "X": 660,
                "Y": -0.27340245333774776
            },
            {
                "X": 661,
                "Y": 0.7994447877701234
            },
            {
                "X": 662,
                "Y": -0.3965077981451041
            },
            {
                "X": 663,
                "Y": -0.5983667002623113
            },
            {
                "X": 664,
                "Y": -1.0761858020366177
            },
            {
                "X": 665,
                "Y": 1.5340079770785056
            },
            {
                "X": 666,
                "Y": 0.5352856409330715
            },
            {
                "X": 667,
                "Y": -1.1696202001214007
            },
            {
                "X": 668,
                "Y": 0.8217572580473391
            },
            {
                "X": 669,
                "Y": -0.9380162525841383
            },
            {
                "X": 670,
                "Y": 1.0374105206934385
            },
            {
                "X": 671,
                "Y": -0.2873596160252127
            },
            {
                "X": 672,
                "Y": -0.19589480842119322
            },
            {
                "X": 673,
                "Y": 0.885911096499419
            },
            {
                "X": 674,
                "Y": -0.3493544326507731
            },
            {
                "X": 675,
                "Y": -0.5606385123818436
            },
            {
                "X": 676,
                "Y": 0.5209211688923385
            },
            {
                "X": 677,
                "Y": 0.9035735767860679
            },
            {
                "X": 678,
                "Y": -1.0531104814477619
            },
            {
                "X": 679,
                "Y": 0.05238297140275595
            },
            {
                "X": 680,
                "Y": 0.27350686434933325
            },
            {
                "X": 681,
                "Y": -0.7732718889457693
            },
            {
                "X": 682,
                "Y": -0.05187250201524271
            },
            {
                "X": 683,
                "Y": 0.21999145676332707
            },
            {
                "X": 684,
                "Y": -0.2347557489088973
            },
            {
                "X": 685,
                "Y": 7.684310256041752
            },
            {
                "X": 686,
                "Y": 0.7302710697186088
            },
            {
                "X": 687,
                "Y": 1.1194083218522675
            },
            {
                "X": 688,
                "Y": 0.5903337706586136
            },
            {
                "X": 689,
                "Y": -1.651247954463953
            },
            {
                "X": 690,
                "Y": 2.2121535715688387
            },
            {
                "X": 691,
                "Y": 10.885211173850976
            },
            {
                "X": 692,
                "Y": -1.2219947859989027
            },
            {
                "X": 693,
                "Y": 0.12545473228070753
            },
            {
                "X": 694,
                "Y": -0.5685232433166842
            },
            {
                "X": 695,
                "Y": -0.5294282348231855
            },
            {
                "X": 696,
                "Y": 0.4232776887542206
            },
            {
                "X": 697,
                "Y": -0.629699013392347
            },
            {
                "X": 698,
                "Y": -0.23785628215471302
            },
            {
                "X": 699,
                "Y": 1.1563073053951896
            },
            {
                "X": 700,
                "Y": 1.2631081747518749
            },
            {
                "X": 701,
                "Y": -0.031644512517043595
            },
            {
                "X": 702,
                "Y": 0.5143769120474647
            },
            {
                "X": 703,
                "Y": 1.194564449184781
            },
            {
                "X": 704,
                "Y": 9.616179756766918
            },
            {
                "X": 705,
                "Y": 5.871083580270467
            },
            {
                "X": 706,
                "Y": -0.7683780075726614
            },
            {
                "X": 707,
                "Y": 0.28906175717183435
            },
            {
                "X": 708,
                "Y": 1.7010803164147903
            },
            {
                "X": 709,
                "Y": -0.04672148929524302
            },
            {
                "X": 710,
                "Y": 0.9062784705519631
            },
            {
                "X": 711,
                "Y": 0.18637370476091977
            },
            {
                "X": 712,
                "Y": 0.1892455672575418
            },
            {
                "X": 713,
                "Y": 0.7189987917105936
            },
            {
                "X": 714,
                "Y": 0.47803556977259953
            },
            {
                "X": 715,
                "Y": 7.526045182697997
            },
            {
                "X": 716,
                "Y": -2.0607508755591724
            },
            {
                "X": 717,
                "Y": -0.8265113335326737
            },
            {
                "X": 718,
                "Y": 1.0591894078739992
            },
            {
                "X": 719,
                "Y": -1.3174590203960126
            },
            {
                "X": 720,
                "Y": -0.47618220308243775
            },
            {
                "X": 721,
                "Y": -1.64775848308659
            },
            {
                "X": 722,
                "Y": -0.6736402019077266
            },
            {
                "X": 723,
                "Y": -2.132411993171073
            },
            {
                "X": 724,
                "Y": 1.1871985889640981
            },
            {
                "X": 725,
                "Y": -0.40129924615517387
            },
            {
                "X": 726,
                "Y": 0.5825676390691363
            },
            {
                "X": 727,
                "Y": -1.8767039452538032
            },
            {
                "X": 728,
                "Y": -0.5396907553524258
            },
            {
                "X": 729,
                "Y": 1.4962053172498946
            },
            {
                "X": 730,
                "Y": -0.07259084285029996
            },
            {
                "X": 731,
                "Y": -1.0334581538513543
            },
            {
                "X": 732,
                "Y": -1.0337365107798486
            },
            {
                "X": 733,
                "Y": -0.47013317565361223
            },
            {
                "X": 734,
                "Y": -0.8157659471275239
            },
            {
                "X": 735,
                "Y": 8.624286707302671
            },
            {
                "X": 736,
                "Y": 1.0170858653854213
            },
            {
                "X": 737,
                "Y": 0.1739695513289903
            },
            {
                "X": 738,
                "Y": 0.13813663710002078
            },
            {
                "X": 739,
                "Y": 0.00022232739454727322
            },
            {
                "X": 740,
                "Y": -0.15206363430317968
            },
            {
                "X": 741,
                "Y": -0.06810915935448618
            },
            {
                "X": 742,
                "Y": -0.633797141343886
            },
            {
                "X": 743,
                "Y": 0.6016964393528721
            },
            {
                "X": 744,
                "Y": 0.8933679613846225
            },
            {
                "X": 745,
                "Y": 1.1573253334456042
            },
            {
                "X": 746,
                "Y": 1.0910382983657985
            },
            {
                "X": 747,
                "Y": 0.6255733223738794
            },
            {
                "X": 748,
                "Y": 0.7623446855711102
            },
            {
                "X": 749,
                "Y": 1.5679528415777237
            },
            {
                "X": 750,
                "Y": -0.17296510708776647
            },
            {
                "X": 751,
                "Y": -0.7733586918153748
            },
            {
                "X": 752,
                "Y": -0.32815013317494285
            },
            {
                "X": 753,
                "Y": 1.7639830476179998
            },
            {
                "X": 754,
                "Y": 0.17588113271501696
            },
            {
                "X": 755,
                "Y": -0.05244490043718782
            },
            {
                "X": 756,
                "Y": -0.3525706565236537
            },
            {
                "X": 757,
                "Y": -0.6676440640177231
            },
            {
                "X": 758,
                "Y": -1.239638701221745
            },
            {
                "X": 759,
                "Y": 0.26262328451557054
            },
            {
                "X": 760,
                "Y": 5.137989015687702
            },
            {
                "X": 761,
                "Y": 0.055132262845095405
            },
            {
                "X": 762,
                "Y": -1.0242142910990548
            },
            {
                "X": 763,
                "Y": -0.40204422755071345
            },
            {
                "X": 764,
                "Y": 2.6914965526550616
            },
            {
                "X": 765,
                "Y": -0.8231354131996568
            },
            {
                "X": 766,
                "Y": -1.5190095265363444
            },
            {
                "X": 767,
                "Y": -0.2516774968982578
            },
            {
                "X": 768,
                "Y": 0.7503319758078261
            },
            {
                "X": 769,
                "Y": 0.6069685741866645
            },
            {
                "X": 770,
                "Y": -0.20545997456747941
            },
            {
                "X": 771,
                "Y": -0.23129134495440803
            },
            {
                "X": 772,
                "Y": 0.6120589621826378
            },
            {
                "X": 773,
                "Y": 0.4762210176326684
            },
            {
                "X": 774,
                "Y": -0.9062015841611453
            },
            {
                "X": 775,
                "Y": 1.2509607268060647
            },
            {
                "X": 776,
                "Y": -2.4765165684301294
            },
            {
                "X": 777,
                "Y": 0.4339254399265732
            },
            {
                "X": 778,
                "Y": 0.15023646043023953
            },
            {
                "X": 779,
                "Y": -2.5928672455836534
            },
            {
                "X": 780,
                "Y": 5.248804676088084
            },
            {
                "X": 781,
                "Y": -0.22895148827599315
            },
            {
                "X": 782,
                "Y": -1.6513487070849082
            },
            {
                "X": 783,
                "Y": 0.5866193398406725
            },
            {
                "X": 784,
                "Y": 2.7713787227622353
            },
            {
                "X": 785,
                "Y": -0.709570906395477
            },
            {
                "X": 786,
                "Y": -0.16746560998077978
            },
            {
                "X": 787,
                "Y": -0.09486622824192192
            },
            {
                "X": 788,
                "Y": 7.69672512561433
            },
            {
                "X": 789,
                "Y": 0.7663440843898657
            },
            {
                "X": 790,
                "Y": 0.6300231726174321
            },
            {
                "X": 791,
                "Y": -1.2062881530276521
            },
            {
                "X": 792,
                "Y": 9.798983470800684
            },
            {
                "X": 793,
                "Y": 1.1685466989666469
            },
            {
                "X": 794,
                "Y": -1.7053443085477207
            },
            {
                "X": 795,
                "Y": 7.144499208442348
            },
            {
                "X": 796,
                "Y": 7.467141332463345
            },
            {
                "X": 797,
                "Y": 1.1562936486045903
            },
            {
                "X": 798,
                "Y": -2.1109775991803397
            },
            {
                "X": 799,
                "Y": -0.6431543140783585
            },
            {
                "X": 800,
                "Y": 1.110708129414286
            },
            {
                "X": 801,
                "Y": 0.6788716549176738
            },
            {
                "X": 802,
                "Y": 1.6985513104237187
            },
            {
                "X": 803,
                "Y": -0.7077567621284213
            },
            {
                "X": 804,
                "Y": 0.6737485614582202
            },
            {
                "X": 805,
                "Y": -0.05517223261529846
            },
            {
                "X": 806,
                "Y": 1.4325167666512462
            },
            {
                "X": 807,
                "Y": -0.3523534749874692
            },
            {
                "X": 808,
                "Y": -0.19655803832662777
            },
            {
                "X": 809,
                "Y": 0.14371537738428208
            },
            {
                "X": 810,
                "Y": 0.20041009641577706
            },
            {
                "X": 811,
                "Y": -0.23165278964426403
            },
            {
                "X": 812,
                "Y": 0.31218478412301204
            },
            {
                "X": 813,
                "Y": -0.7114737673950183
            },
            {
                "X": 814,
                "Y": 6.15552285053044
            },
            {
                "X": 815,
                "Y": 0.47622080564337915
            },
            {
                "X": 816,
                "Y": 2.3603869935618245
            },
            {
                "X": 817,
                "Y": 0.7068922201837591
            },
            {
                "X": 818,
                "Y": -1.2892971395815243
            },
            {
                "X": 819,
                "Y": -0.12148111737087788
            },
            {
                "X": 820,
                "Y": -0.7755391828773673
            },
            {
                "X": 821,
                "Y": 0.5942063115679126
            },
            {
                "X": 822,
                "Y": -1.2536730178828983
            },
            {
                "X": 823,
                "Y": 0.3392886472385709
            },
            {
                "X": 824,
                "Y": 0.03784961078816756
            },
            {
                "X": 825,
                "Y": 1.3318370274437101
            },
            {
                "X": 826,
                "Y": 0.14507610999956755
            },
            {
                "X": 827,
                "Y": 0.21039681562544413
            },
            {
                "X": 828,
                "Y": 0.21024373582312406
            },
            {
                "X": 829,
                "Y": 1.209693123712457
            },
            {
                "X": 830,
                "Y": 0.34085788659305505
            },
            {
                "X": 831,
                "Y": 0.8912546759213801
            },
            {
                "X": 832,
                "Y": 1.3581409045210033
            },
            {
                "X": 833,
                "Y": -0.9444770286252424
            },
            {
                "X": 834,
                "Y": 0.7623154643114999
            },
            {
                "X": 835,
                "Y": 0.6321984652858369
            },
            {
                "X": 836,
                "Y": 0.46382067052003684
            },
            {
                "X": 837,
                "Y": 1.7321653368547234
            },
            {
                "X": 838,
                "Y": 1.0421405698535733
            },
            {
                "X": 839,
                "Y": 0.5465429204536272
            },
            {
                "X": 840,
                "Y": 1.690702624651472
            },
            {
                "X": 841,
                "Y": 7.025753301690467
            },
            {
                "X": 842,
                "Y": 1.534109356531381
            },
            {
                "X": 843,
                "Y": -0.3898584234683555
            },
            {
                "X": 844,
                "Y": 0.10303062106435601
            },
            {
                "X": 845,
                "Y": -0.7702971758823671
            },
            {
                "X": 846,
                "Y": 2.8321928226189006
            },
            {
                "X": 847,
                "Y": 1.027638968730755
            },
            {
                "X": 848,
                "Y": -0.6398418273551412
            },
            {
                "X": 849,
                "Y": -1.1484966916901678
            },
            {
                "X": 850,
                "Y": 0.9998287866475186
            },
            {
                "X": 851,
                "Y": 0.2573424967931495
            },
            {
                "X": 852,
                "Y": -1.0080101775057797
            },
            {
                "X": 853,
                "Y": 0.5412340042160696
            },
            {
                "X": 854,
                "Y": 1.5458846951913556
            },
            {
                "X": 855,
                "Y": -1.7748080240764936
            },
            {
                "X": 856,
                "Y": 0.309324303599507
            },
            {
                "X": 857,
                "Y": -0.6104597767821351
            },
            {
                "X": 858,
                "Y": 0.16359006333985213
            },
            {
                "X": 859,
                "Y": -0.06290823041317817
            },
            {
                "X": 860,
                "Y": -0.7338956367289615
            },
            {
                "X": 861,
                "Y": 0.763823305366944
            },
            {
                "X": 862,
                "Y": -1.333922561993211
            },
            {
                "X": 863,
                "Y": -1.8396119785040552
            },
            {
                "X": 864,
                "Y": 1.3637479782789532
            },
            {
                "X": 865,
                "Y": -1.2051685804581216
            },
            {
                "X": 866,
                "Y": 0.08294498315079651
            },
            {
                "X": 867,
                "Y": 0.5318737252775668
            },
            {
                "X": 868,
                "Y": -0.3806906640940521
            },
            {
                "X": 869,
                "Y": -0.7130991728678333
            },
            {
                "X": 870,
                "Y": -0.10209662754866025
            },
            {
                "X": 871,
                "Y": -0.5997989189200227
            },
            {
                "X": 872,
                "Y": -0.2537948359785781
            },
            {
                "X": 873,
                "Y": 0.5871617378981073
            },
            {
                "X": 874,
                "Y": 0.5076990738122236
            },
            {
                "X": 875,
                "Y": 0.048765594686884406
            },
            {
                "X": 876,
                "Y": -0.13935539148183346
            },
            {
                "X": 877,
                "Y": -1.0183585993484798
            },
            {
                "X": 878,
                "Y": 0.7885765014711943
            },
            {
                "X": 879,
                "Y": 0.3669609143395435
            },
            {
                "X": 880,
                "Y": 0.7803332406111179
            },
            {
                "X": 881,
                "Y": 1.021338030455411
            },
            {
                "X": 882,
                "Y": 0.4017942223043529
            },
            {
                "X": 883,
                "Y": -1.1988635061982633
            },
            {
                "X": 884,
                "Y": -1.763755535109151
            },
            {
                "X": 885,
                "Y": -0.0610576685691945
            },
            {
                "X": 886,
                "Y": 0.6658792386392361
            },
            {
                "X": 887,
                "Y": 1.2536740337824663
            },
            {
                "X": 888,
                "Y": -1.1867785591221898
            },
            {
                "X": 889,
                "Y": 1.5740451461441871
            },
            {
                "X": 890,
                "Y": -0.36939189955732366
            },
            {
                "X": 891,
                "Y": 1.5182427068285935
            },
            {
                "X": 892,
                "Y": -1.5715714684843727
            },
            {
                "X": 893,
                "Y": -0.29820562174082543
            },
            {
                "X": 894,
                "Y": -0.2508553596474077
            },
            {
                "X": 895,
                "Y": -0.8219920862591381
            },
            {
                "X": 896,
                "Y": -1.104623267653569
            },
            {
                "X": 897,
                "Y": 1.0631783152651728
            },
            {
                "X": 898,
                "Y": -1.1531287638101226
            },
            {
                "X": 899,
                "Y": 0.5150400818427809
            },
            {
                "X": 900,
                "Y": -0.7900769960222108
            },
            {
                "X": 901,
                "Y": -0.8573657954127706
            },
            {
                "X": 902,
                "Y": 0.21790499337152386
            },
            {
                "X": 903,
                "Y": 1.3967808832977195
            },
            {
                "X": 904,
                "Y": 0.5230116365537849
            },
            {
                "X": 905,
                "Y": -0.06055424049681378
            },
            {
                "X": 906,
                "Y": -0.5190406168814939
            },
            {
                "X": 907,
                "Y": -2.2658361579445354
            },
            {
                "X": 908,
                "Y": 1.2905902748061182
            },
            {
                "X": 909,
                "Y": 1.1356992900292175
            },
            {
                "X": 910,
                "Y": 0.44380228999052745
            },
            {
                "X": 911,
                "Y": -1.4416487351692513
            },
            {
                "X": 912,
                "Y": -0.6050027279528191
            },
            {
                "X": 913,
                "Y": -0.22609153341791452
            },
            {
                "X": 914,
                "Y": 0.008360421982145767
            },
            {
                "X": 915,
                "Y": 0.6016452876942004
            },
            {
                "X": 916,
                "Y": -1.1098894067130407
            },
            {
                "X": 917,
                "Y": -1.0057227359857968
            },
            {
                "X": 918,
                "Y": -0.959088361469558
            },
            {
                "X": 919,
                "Y": -1.7166989169106672
            },
            {
                "X": 920,
                "Y": 1.887775949929996
            },
            {
                "X": 921,
                "Y": -0.030396596854534146
            },
            {
                "X": 922,
                "Y": 0.5012249372930785
            },
            {
                "X": 923,
                "Y": 0.8260060732312402
            },
            {
                "X": 924,
                "Y": 1.224617018331876
            },
            {
                "X": 925,
                "Y": 0.14596432459276396
            },
            {
                "X": 926,
                "Y": 1.8260912931739988
            },
            {
                "X": 927,
                "Y": 0.02137036207213163
            },
            {
                "X": 928,
                "Y": -1.6493923004385171
            },
            {
                "X": 929,
                "Y": 1.0196556431829282
            },
            {
                "X": 930,
                "Y": -0.17515800420547653
            },
            {
                "X": 931,
                "Y": -1.8164400862929346
            },
            {
                "X": 932,
                "Y": -0.7306405764920687
            },
            {
                "X": 933,
                "Y": 0.06808558576835706
            },
            {
                "X": 934,
                "Y": 0.043998330973122377
            },
            {
                "X": 935,
                "Y": -0.22624170058525367
            },
            {
                "X": 936,
                "Y": 10.506018475476873
            },
            {
                "X": 937,
                "Y": -1.0873261902052724
            },
            {
                "X": 938,
                "Y": 0.027380592591267554
            },
            {
                "X": 939,
                "Y": -0.141935313648986
            },
            {
                "X": 940,
                "Y": 0.7828692165014518
            },
            {
                "X": 941,
                "Y": -0.7060022886003119
            },
            {
                "X": 942,
                "Y": -0.6576545377266725
            },
            {
                "X": 943,
                "Y": 1.0017502055364984
            },
            {
                "X": 944,
                "Y": 0.19840495514841378
            },
            {
                "X": 945,
                "Y": 1.4742483063056058
            },
            {
                "X": 946,
                "Y": -1.3837847893934552
            },
            {
                "X": 947,
                "Y": 0.4432586163185466
            },
            {
                "X": 948,
                "Y": 0.3759118898349467
            },
            {
                "X": 949,
                "Y": -0.8439255092601282
            },
            {
                "X": 950,
                "Y": -0.7170166987415197
            },
            {
                "X": 951,
                "Y": 1.7538795579814614
            },
            {
                "X": 952,
                "Y": 1.6433687128318377
            },
            {
                "X": 953,
                "Y": -0.16114617000851625
            },
            {
                "X": 954,
                "Y": -1.413517608937937
            },
            {
                "X": 955,
                "Y": -1.3062970225826804
            },
            {
                "X": 956,
                "Y": 0.2223300084025623
            },
            {
                "X": 957,
                "Y": 0.9745590462317714
            },
            {
                "X": 958,
                "Y": -1.612965667981802
            },
            {
                "X": 959,
                "Y": -0.22255336104281756
            },
            {
                "X": 960,
                "Y": -1.2613282163880062
            },
            {
                "X": 961,
                "Y": 0.8121427304275538
            },
            {
                "X": 962,
                "Y": 6.658139228775544
            },
            {
                "X": 963,
                "Y": 0.9442946800511177
            },
            {
                "X": 964,
                "Y": 1.1483337218194
            },
            {
                "X": 965,
                "Y": 0.8370886062173828
            },
            {
                "X": 966,
                "Y": 8.154889474141436
            },
            {
                "X": 967,
                "Y": -0.024179397588768792
            },
            {
                "X": 968,
                "Y": -0.15118844550985883
            },
            {
                "X": 969,
                "Y": -0.939208712719144
            },
            {
                "X": 970,
                "Y": -0.8012580654166275
            },
            {
                "X": 971,
                "Y": 0.08096006114971507
            },
            {
                "X": 972,
                "Y": -1.196157199716775
            },
            {
                "X": 973,
                "Y": 3.7425250428878045
            },
            {
                "X": 974,
                "Y": 0.6248337428286279
            },
            {
                "X": 975,
                "Y": 8.91743355760782
            },
            {
                "X": 976,
                "Y": 0.4035183906306782
            },
            {
                "X": 977,
                "Y": 1.9237523351897368
            },
            {
                "X": 978,
                "Y": 0.3190471329951484
            },
            {
                "X": 979,
                "Y": -3.353537863806189
            },
            {
                "X": 980,
                "Y": -1.1829434146839448
            },
            {
                "X": 981,
                "Y": -1.296094947815688
            },
            {
                "X": 982,
                "Y": 0.5333036369549111
            },
            {
                "X": 983,
                "Y": 0.17796520515860223
            },
            {
                "X": 984,
                "Y": -1.0600223501804726
            },
            {
                "X": 985,
                "Y": -0.09807849843004032
            },
            {
                "X": 986,
                "Y": -1.9698665837484268
            },
            {
                "X": 987,
                "Y": -1.0216327557490372
            },
            {
                "X": 988,
                "Y": -0.9038942496725592
            },
            {
                "X": 989,
                "Y": -0.794835303627912
            },
            {
                "X": 990,
                "Y": -1.3848491531473546
            },
            {
                "X": 991,
                "Y": 0.6756980810873426
            },
            {
                "X": 992,
                "Y": -0.013399991853295523
            },
            {
                "X": 993,
                "Y": 1.1111795214414821
            },
            {
                "X": 994,
                "Y": 0.17241696995927858
            },
            {
                "X": 995,
                "Y": -1.5832743172475057
            },
            {
                "X": 996,
                "Y": 1.653885523539249
            },
            {
                "X": 997,
                "Y": 0.7512520738251547
            },
            {
                "X": 998,
                "Y": -0.2611128439880819
            },
            {
                "X": 999,
                "Y": -0.39770639030615285
            },
            {
                "X": 1000,
                "Y": -0.6779133551736201
            }
        ],
        "analysis_report": {
            "knn5_mean": -2.575829034672121,
            "knn5_std": 0.7284996577266981,
            "local_dim5_mean": 1.871,
            "local_dim5_std": 0.33519994033412354,
            "knn10_mean": -2.2668230258032454,
            "knn10_std": 0.7166051084613876,
            "local_dim10_mean": 1.993,
            "local_dim10_std": 0.08337265738837882,
            "knn20_mean": -1.942675540325972,
            "knn20_std": 0.7095062307216101,
            "local_dim20_mean": 1.998,
            "local_dim20_std": 0.044676615807377355,
            "global_dim90": 2,
            "ev1": 0.5534190810565104,
            "ev2": 0.44658091894348967,
            "ev3": 0.0,
            "tda_betti0": 0.0,
            "tda_betti1": 0.0,
            "tda_life_mean": 0.0,
            "tda_life_max": 0.0,
            "hurst": 0.9981253837777596,
            "fractal_dim": 1.0,
            "mf_width": 1.7763568394002505e-15,
            "mf_singularity": 2.010657190759645,
            "mf_asymmetry": 1.0,
            "fisher": 0.0372975705854813,
            "rqa_rr": 0.0998008040128353,
            "rqa_det": 0.010029979276070904,
            "var": 0.9999999999999998,
            "entropy": 11.478645343986027
        }
    }
}